{
  "version": "1.0",
  "generatedAt": "2026-03-17T23:00:46.069Z",
  "source": "milady-ai/trust-dashboard",
  "username": "OkeyGoogle1",
  "profile": {
    "username": "OkeyGoogle1",
    "canonicalUsername": "okeygoogle1",
    "avatarUrl": "https://avatars.githubusercontent.com/u/237472336?v=4",
    "milady": {
      "trustScore": 17.61,
      "rank": 46,
      "tier": "untested"
    },
    "eliza": null,
    "ecosystemFactor": 0,
    "elizaEffect": {
      "miladyNorm": 0.1761,
      "elizaLifetimePercentile": 0,
      "ecosystemNorm": 0,
      "weights": {
        "milady": 0.45,
        "eliza": 0.35,
        "ecosystem": 0.2
      },
      "effectNorm": 0.079245,
      "effectScore": 7.9245
    }
  }
}
